ligand_workflow/_00_align_ligand.py
ligand_workflow/_10_calculate_contacts.py
ligand_workflow/_20_convert_json_to_csv.py
ligand_workflow/__init__.py
ligand_workflow/ligand_workflow.py
ligand_workflow-0.0.8.dist-info/METADATA
ligand_workflow-0.0.8.dist-info/WHEEL
ligand_workflow-0.0.8.dist-info/entry_points.txt
ligand_workflow-0.0.8.dist-info/top_level.txt
ligand_workflow-0.0.8.dist-info/RECORD
