Metadata-Version: 2.1
Name: ligand_workflow
Version: 0.0.8
Summary: A workflow for aligning ligands and calculating contacts.
Home-page: https://github.com/OOAAHH/ligand_workflow
Author: Hao Sun
Author-email: sun_hao@gzlab.ac.cn
Classifier: Programming Language :: Python :: 3
Classifier: License :: OSI Approved :: MIT License
Classifier: Operating System :: OS Independent
Requires-Dist: pymol
Requires-Dist: numpy
Requires-Dist: argparse
